.clang-format
DEVNOTES.md
HISTORY.rst
LICENSE
MANIFEST.in
Makefile
README.rst
psleak.py
pyproject.toml
psleak.egg-info/PKG-INFO
psleak.egg-info/SOURCES.txt
psleak.egg-info/dependency_links.txt
psleak.egg-info/requires.txt
psleak.egg-info/top_level.txt
tests/__init__.py
tests/build_ext.py
tests/test_algo.py
tests/test_c_leaks.py
tests/test_ext.c
tests/test_interface.py
tests/test_python_leaks.py