Metadata-Version: 2.4
Name: psleak
Version: 0.1.2
Summary: Detect memory and resource leaks in Python C extensions
Author-email: Giampaolo Rodola <g.rodola@gmail.com>
License-Expression: BSD-3-Clause
Project-URL: Homepage, https://github.com/giampaolo/psleak
Classifier: Development Status :: 4 - Beta
Classifier: Intended Audience :: Developers
Classifier: Operating System :: OS Independent
Classifier: Programming Language :: Python :: 3
Classifier: Topic :: Software Development :: Debuggers
Classifier: Topic :: Software Development :: Testing
Classifier: Topic :: System :: Monitoring
Requires-Python: >=3.6
License-File: LICENSE
Requires-Dist: psutil>=7.2
Provides-Extra: test
Requires-Dist: pytest; extra == "test"
Requires-Dist: pytest-instafail; extra == "test"
Provides-Extra: linters
Requires-Dist: build; extra == "linters"
Requires-Dist: twine; extra == "linters"
Requires-Dist: validate-pyproject; extra == "linters"
Dynamic: license-file
